text2topicloss/__init__.py
text2topicloss/text2topicLoss.py
text2topicloss-1.0.0.dist-info/LICENSE
text2topicloss-1.0.0.dist-info/METADATA
text2topicloss-1.0.0.dist-info/WHEEL
text2topicloss-1.0.0.dist-info/top_level.txt
text2topicloss-1.0.0.dist-info/RECORD
