Metadata-Version: 2.1
Name: text2topicloss
Version: 1.0.0
Summary: Text2topic loss for bi-encoder models
Author-email: Marc-Alexis Azaïs <azaismarc.pro@gmail.com>
Project-URL: Repository, https://github.com/azaismarc/text2topic
Project-URL: Paper, https://aclanthology.org/2023.emnlp-industry.10/
Keywords: text2topic,nlp,topic modeling,BERT,BERTopic
Classifier: Development Status :: 5 - Production/Stable
Classifier: Intended Audience :: Science/Research
Classifier: Intended Audience :: Developers
Classifier: Intended Audience :: Customer Service
Classifier: Topic :: Text Processing
Classifier: Topic :: Scientific/Engineering :: Artificial Intelligence
Classifier: License :: OSI Approved :: GNU General Public License v3 or later (GPLv3+)
Classifier: Programming Language :: Python :: 3
License-File: LICENSE
Requires-Dist: sentence-transformers
